jsonconv/__init__.py
jsonconv/common.py
jsonconv/csv.py
jsonconv/html.py
jsonconv/sql.py
jsonconv-0.0.1.dist-info/METADATA
jsonconv-0.0.1.dist-info/RECORD
jsonconv-0.0.1.dist-info/WHEEL
jsonconv-0.0.1.dist-info/top_level.txt
