Metadata-Version: 2.1
Name: jsonconv
Version: 0.0.1
Summary: Simple library for converting some data structures to/from JSON
Home-page: https://github.com/ctrl-q/jsonconv
Author: ctrl-q
Author-email: 
License: GPLv3
Platform: UNKNOWN
Classifier: License :: OSI Approved :: GNU General Public License v3 (GPLv3)
Classifier: Programming Language :: Python
Classifier: Programming Language :: Python :: 3
Classifier: Programming Language :: Python :: 3.6
Classifier: Programming Language :: Python :: Implementation :: CPython
Classifier: Programming Language :: Python :: Implementation :: PyPy
Requires-Python: >=3.0.0
